awsome_runner.py
setup.py
OpsletsEc2.egg-info/PKG-INFO
OpsletsEc2.egg-info/SOURCES.txt
OpsletsEc2.egg-info/dependency_links.txt
OpsletsEc2.egg-info/entry_points.txt
OpsletsEc2.egg-info/requires.txt
OpsletsEc2.egg-info/top_level.txt
awsome/__init__.py
awsome/ec2nodesls.py
awsome/elbnodesls.py
awsome/jinjaTemplate.py
awsome/resultClass.py
config/__init__.py
config/env_config.py
config/loggers.py