Metadata-Version: 1.1
Name: OpsletsEc2
Version: 0.3.30
Summary: DevOps life helpers.
Home-page: www.grosu.io
Author: Yair Grosu, Zaidan Sheabar
Author-email: yair@grosu.io
License: UNKNOWN
Platform: UNKNOWN
Classifier: Development Status :: 3 - Alpha
Classifier: Environment :: Console
Classifier: Intended Audience :: End Users/Desktop
Classifier: Intended Audience :: Developers
Classifier: Intended Audience :: System Administrators
Classifier: License :: OSI Approved :: BSD License
Classifier: Operating System :: MacOS :: MacOS X
Classifier: Operating System :: Unix
Classifier: Operating System :: POSIX
Classifier: Programming Language :: Python
Classifier: Topic :: System :: Shells
Classifier: Topic :: Utilities
